callscript/__init__.py
callscript/_version.py
callscript/callscript.py
callscript/cli.py
callscript/redbaron_utils.py
callscript-0.7.2.dist-info/LICENSE.txt
callscript-0.7.2.dist-info/METADATA
callscript-0.7.2.dist-info/WHEEL
callscript-0.7.2.dist-info/entry_points.txt
callscript-0.7.2.dist-info/top_level.txt
callscript-0.7.2.dist-info/RECORD
