Metadata-Version: 2.1
Name: callscript
Version: 0.7.2
Summary: Makes scripts feel like functions.
Author-email: "Nicholas A. Del Grosso" <delgrosso.nick@gmail.com>
Maintainer-email: "Nicholas A. Del Grosso" <delgrosso.nick@gmail.com>
License: MIT License
Project-URL: repository, https://github.com/nickdelgrosso/callscript
Project-URL: changelog, https://github.com/nickdelgrosso/callscript/blob/main/CHANGELOG.md
Classifier: Programming Language :: Python
Requires-Python: >=3.8
License-File: LICENSE.txt
Requires-Dist: redbaron
Provides-Extra: dev
Requires-Dist: pytest ; extra == 'dev'
Requires-Dist: pytest-cov[all] ; extra == 'dev'
Requires-Dist: tox ; extra == 'dev'
Requires-Dist: scriv[toml] ; extra == 'dev'
